{
    "animal_id":"1.5.20_AB2",
    "rc":"true",
    "stim_mA":1.0,
    "stim_duration_min":20,
    "stim_freq_hz":5,
    "type":"stim",
    "species":"C57b6",
    "samples":{
        "source":{
            "spleen":{
                "time_hour":{
                    "1":{
                        "treatment":{
                            "none":{
                                "analytes":{
                                    "nk_percent_1":null,
                                    "nk_percent_2":null,
                                    "cd69_percent_1":null,
                                    "cd69_percent_2":null
                                }
                            }
                        }
                    },
                    "2":{
                        "treatment":{
                            "none":{
                                "analytes":{
                                    "nk_percent_1":1.425,
                                    "nk_percent_2":1.467,
                                    "cd69_percent_1":21.705,
                                    "cd69_percent_2":21.622
                                }
                            }
                        }
                    },
                    "24":{
                        "treatment":{
                            "none":{
                                "analytes":{
                                    "nk_percent_1":null,
                                    "nk_percent_2":null,
                                    "cd69_percent_1":null,
                                    "cd69_percent_2":null
                                }
                            }
                        }
                    }
                }
            },
            "peripheral":{
                "time_hour":{
                    "0":{
                        "treatment":{
                            "none":{
                                "analytes":{
                                    "nk_percent_1":3.0287,
                                    "nk_percent_2":2.8752,
                                    "cd69_percent_1":16.0839,
                                    "cd69_percent_2":15.5932,
                                    "delta_nk_percent":0,
                                    "delta_cd69":0
                                }
                            }
                        }
                    },
                    "1":{
                        "treatment":{
                            "none":{
                                "analytes":{
                                    "nk_percent_1":null,
                                    "nk_percent_2":null,
                                    "cd69_percent_1":null,
                                    "cd69_percent_2":null,
                                    "delta_nk_percent":null,
                                    "delta_cd69":null
                                }
                            }
                        }
                    },
                    "2":{
                        "treatment":{
                            "none":{
                                "analytes":{
                                    "nk_percent_1":2.7453,
                                    "nk_percent_2":null,
                                    "cd69_percent_1":5.2174,
                                    "cd69_percent_2":null,
                                    "delta_nk_percent":-7.0016,
                                    "delta_cd69":-67.0589
                                }
                            }
                        }
                    },
                    "24":{
                        "treatment":{
                            "none":{
                                "analytes":{
                                    "nk_percent_1":null,
                                    "nk_percent_2":null,
                                    "cd69_percent_1":null,
                                    "cd69_percent_2":null,
                                    "delta_nk_percent":null,
                                    "delta_cd69":null
                                }
                            }
                        }
                    }
                }
            }
        }
    }
}