{
    "animal_id":"1_10_20_TM1",
    "rc":"false",
    "stim_mA":null,
    "stim_duration_min":20,
    "stim_freq_hz":null,
    "type":"sham",
    "species":"sprague-dawley",
    "samples":{
        "source":{
            "peripheral":{
                "time_min":{
                    "0":{
                        "treatment":{
                            "none":{
                                "analytes":{
                                    "nk_percent_1":2.53,
                                    "nk_percent_2":2.53,
                                    "tcell_percent_1":40.59,
                                    "tcell_percent_2":40.59,
                                    "cytotoxic_t_percent_1":2.696,
                                    "cytotoxic_t_percent_2":2.696,
                                    "epinephrine_1":null,
                                    "epinephrine_2":null
                                }
                            }
                        }
                    },
                    "20":{
                        "treatment":{
                            "none":{
                                "analytes":{
                                    "nk_percent_1":2.92,
                                    "nk_percent_2":2.92,
                                    "tcell_percent_1":44.432,
                                    "tcell_percent_2":44.432,
                                    "cytotoxic_t_percent_1":2.578,
                                    "cytotoxic_t_percent_2":2.578,
                                    "epinephrine_1":null,
                                    "epinephrine_2":null
                                }
                            }
                        }
                    },
                    "80":{
                        "treatment":{
                            "none":{
                                "analytes":{
                                    "nk_percent_1":4.601,
                                    "nk_percent_2":4.601,
                                    "tcell_percent_1":48.555,
                                    "tcell_percent_2":48.555,
                                    "cytotoxic_t_percent_1":2.39,
                                    "cytotoxic_t_percent_2":2.39,
                                    "epinephrine_1":null,
                                    "epinephrine_2":null
                                }
                            }
                        }
                    },
                    "140":{
                        "treatment":{
                            "none":{
                                "analytes":{
                                    "nk_percent_1":null,
                                    "nk_percent_2":null,
                                    "tcell_percent_1":null,
                                    "tcell_percent_2":null,
                                    "cytotoxic_t_percent_1":null,
                                    "cytotoxic_t_percent_2":null,
                                    "epinephrine_1":null,
                                    "epinephrine_2":null
                                }
                            }
                        }
                    },
                    "200":{
                        "treatment":{
                            "none":{
                                "analytes":{
                                    "nk_percent_1":null,
                                    "nk_percent_2":null,
                                    "tcell_percent_1":null,
                                    "tcell_percent_2":null,
                                    "cytotoxic_t_percent_1":null,
                                    "cytotoxic_t_percent_2":null,
                                    "epinephrine_1":null,
                                    "epinephrine_2":null
                                }
                            }
                        }
                    }
                }
            }
        }
    }
}